protoc_gen_mavsdk/__init__.py
protoc_gen_mavsdk/__main__.py
protoc_gen_mavsdk/autogen.py
protoc_gen_mavsdk/autogen_file.py
protoc_gen_mavsdk/docs.py
protoc_gen_mavsdk/mavsdk_options_pb2.py
protoc_gen_mavsdk/methods.py
protoc_gen_mavsdk/name_parser.py
protoc_gen_mavsdk/pb_enum.py
protoc_gen_mavsdk/pb_struct.py
protoc_gen_mavsdk/type_info.py
protoc_gen_mavsdk/utils.py
protoc_gen_mavsdk-1.3.0.dist-info/METADATA
protoc_gen_mavsdk-1.3.0.dist-info/WHEEL
protoc_gen_mavsdk-1.3.0.dist-info/entry_points.txt
protoc_gen_mavsdk-1.3.0.dist-info/top_level.txt
protoc_gen_mavsdk-1.3.0.dist-info/RECORD
