Metadata-Version: 2.1
Name: protoc-gen-mavsdk
Version: 1.3.0
Summary: Protoc plugin used to generate MAVSDK bindings
Home-page: https://github.com/mavlink/MAVSDK-Proto
Maintainer: Jonas Vautherin, Julian Oes
Maintainer-email: dev@jonas.vautherin.ch, julian@oes.ch
Classifier: Development Status :: 5 - Production/Stable
Classifier: Intended Audience :: Developers
Classifier: License :: OSI Approved :: BSD License
Requires-Dist: jinja2 >=3.1.4
Requires-Dist: protobuf >=6.32.1
